agents/__init__.py
agents/agent.py
agents/deep_policy_gradient.py
agents/deep_q.py
agents/policy_gradient.py
agents/random_agent.py
control/__init__.py
control/controller.py
control/controller_centralized.py
control/controller_centralized_RL.py
control/controller_decentralized.py
control/controller_decentralized_RL.py
control/controller_economic.py
control/evaluate.py
environments/__init__.py
environments/env_wrapper.py
environments/MultiTaxiEnv/__init__.py
environments/MultiTaxiEnv/config.py
environments/MultiTaxiEnv/taxi_environment.py
environments/MultiTaxiEnv/taxi_task_agent.py
environments/cleanup/__init__.py
environments/cleanup/example.py
environments/cleanup/utility_funcs.py
environments/corners/__init__.py
environments/corners/corners_agents.py
environments/corners/corners_env.py
multi_agent_control-0.0.2.dist-info/LICENSE.md
multi_agent_control-0.0.2.dist-info/METADATA
multi_agent_control-0.0.2.dist-info/WHEEL
multi_agent_control-0.0.2.dist-info/top_level.txt
multi_agent_control-0.0.2.dist-info/RECORD
