Metadata-Version: 2.1
Name: multi-agent-control
Version: 0.0.2
Summary: A framework for multi agent control
Home-page: https://github.com/sarah-keren/MAC
Author: Boaz Bibi
License: UNKNOWN
Platform: UNKNOWN
Classifier: Programming Language :: Python :: 3
Classifier: License :: OSI Approved :: MIT License
Classifier: Operating System :: OS Independent
Requires-Python: >=3.6
License-File: LICENSE.md
